urls2s3/__init__.py
urls2s3/datatypes.py
urls2s3/main.py
urls2s3/misc_functions.py
urls2s3-0.1.0.dist-info/WHEEL
urls2s3-0.1.0.dist-info/METADATA
urls2s3-0.1.0.dist-info/RECORD
