Metadata-Version: 2.1
Name: urls2s3
Version: 0.1.0
Summary: 
Author: lemerchand
Author-email: phoenix.scooter@gmail.com
Requires-Python: >=3.10,<4.0
Classifier: Programming Language :: Python :: 3
Classifier: Programming Language :: Python :: 3.10
Requires-Dist: boto3 (>=1.24.61,<2.0.0)
Requires-Dist: pandas (>=1.4.3,<2.0.0)
Requires-Dist: requests (>=2.28.1,<3.0.0)
Requires-Dist: rich (>=12.5.1,<13.0.0)
